cpunetlog/__init__.py
cpunetlog/__main__.py
cpunetlog/curses_display.py
cpunetlog/helpers.py
cpunetlog/history_store.py
cpunetlog/logging.py
cpunetlog/main.py
cpunetlog/psutil_functions.py
cpunetlog/testing.py
cpunetlog-1.1.1.dist-info/DESCRIPTION.rst
cpunetlog-1.1.1.dist-info/METADATA
cpunetlog-1.1.1.dist-info/RECORD
cpunetlog-1.1.1.dist-info/WHEEL
cpunetlog-1.1.1.dist-info/entry_points.txt
cpunetlog-1.1.1.dist-info/metadata.json
cpunetlog-1.1.1.dist-info/top_level.txt
