Metadata-Version: 2.0
Name: cpunetlog
Version: 1.1.1
Summary: Display, log and plot CPU utilization and network throughput
Home-page: https://git.scc.kit.edu/CPUnetLOG/CPUnetLOG
Author: Mario Hock
Author-email: mario.hock@kit.edu
License: BSD
Keywords: cpu,throughput,utilization,plot,log,display,analyze,network,traffic
Platform: Linux
Classifier: Development Status :: 5 - Production/Stable
Classifier: License :: OSI Approved :: BSD License
Classifier: Programming Language :: Python :: 3
Classifier: Operating System :: POSIX :: Linux
Classifier: Environment :: Console
Classifier: Environment :: Console :: Curses
Classifier: Natural Language :: English
Classifier: Intended Audience :: Education
Classifier: Intended Audience :: Information Technology
Classifier: Intended Audience :: Science/Research
Classifier: Intended Audience :: System Administrators
Classifier: Intended Audience :: Telecommunications Industry
Classifier: Topic :: Scientific/Engineering
Classifier: Topic :: Internet
Classifier: Topic :: System :: Logging
Classifier: Topic :: System :: Networking
Classifier: Topic :: System :: Networking :: Monitoring
Classifier: Topic :: System :: Operating System Kernels :: Linux
Classifier: Topic :: Utilities
Requires-Dist: netifaces
Requires-Dist: psutil
